Metadata-Version: 2.1
Name: geta
Version: 0.1.0
Summary: geta, for when you need to "get a" random thing
Home-page: https://github.com/shnewto/geta
Author: Shea Newton
Author-email: shnewto@gmail.com
License: UNKNOWN
Download-URL: https://github.com/shnewto/geta/archive/0.1.0.tar.gz
Platform: UNKNOWN
Classifier: Programming Language :: Python :: 3
Classifier: License :: OSI Approved :: MIT License
Classifier: Operating System :: OS Independent
Requires-Python: >=3.6
